{"trial_id": "31", "hyperparameters": {"space": [{"class_name": "Int", "config": {"name": "units", "default": null, "conditions": [], "min_value": 48, "max_value": 144, "step": 16, "sampling": "linear"}}, {"class_name": "Float", "config": {"name": "learning_rate", "default": 0.0001, "conditions": [], "min_value": 0.0001, "max_value": 1.0, "step": 10, "sampling": "log"}}], "values": {"units": 128, "learning_rate": 1.0}}, "metrics": {"metrics": {"huber": {"direction": "min", "observations": [{"value": [29.691125869750977], "step": 1}]}, "loss": {"direction": "min", "observations": [{"value": [122.27960968017578], "step": 1}]}, "val_huber": {"direction": "min", "observations": [{"value": [230.42955017089844], "step": 1}]}, "val_loss": {"direction": "min", "observations": [{"value": [95.720703125], "step": 1}]}}}, "score": 95.720703125, "best_step": 1, "status": "COMPLETED", "message": null}